[
    {
        "name": "Diogo",
        "startPoint": "Idaho",
        "startTime": "08:15:00",
        "vehicle": "car"
    },
    {
        "name": "Sandra",
        "startPoint": "Tennessee",
        "startTime": "08:30:00",
        "vehicle": "bike"
    },
    {
        "name": "Joao",
        "startPoint": "Michigan",
        "startTime": "08:45:00",
        "vehicle": "car"
    },
    {
        "name": "Pedro",
        "startPoint": "New York",
        "startTime": "09:00:00",
        "vehicle": "scooter"
    }
]